{
  "stats": {
    "minecraft:custom": {
      "minecraft:sprint_one_cm": 527,
      "minecraft:time_since_rest": 2672,
      "minecraft:walk_one_cm": 231,
      "minecraft:total_world_time": 3069,
      "minecraft:leave_game": 1,
      "minecraft:fly_one_cm": 10081,
      "minecraft:walk_under_water_one_cm": 56,
      "minecraft:walk_on_water_one_cm": 68,
      "minecraft:sneak_time": 17,
      "minecraft:play_time": 2672,
      "minecraft:jump": 6,
      "minecraft:time_since_death": 2672
    }
  },
  "DataVersion": 4671
}